dcs_catalog_client/__init__.py
dcs_catalog_client/api_client.py
dcs_catalog_client/configuration.py
dcs_catalog_client/rest.py
dcs_catalog_client/api/__init__.py
dcs_catalog_client/api/misc_api.py
dcs_catalog_client/api/v3_api.py
dcs_catalog_client/api/v4_api.py
dcs_catalog_client/api/v5_api.py
dcs_catalog_client/models/__init__.py
dcs_catalog_client/models/access_token.py
dcs_catalog_client/models/attachment.py
dcs_catalog_client/models/catalog_search_results_pivoted_v3.py
dcs_catalog_client/models/catalog_search_results_v3.py
dcs_catalog_client/models/catalog_search_results_v4.py
dcs_catalog_client/models/catalog_search_results_v5.py
dcs_catalog_client/models/catalog_stage.py
dcs_catalog_client/models/catalog_stages.py
dcs_catalog_client/models/catalog_v3.py
dcs_catalog_client/models/catalog_v3_language.py
dcs_catalog_client/models/catalog_v3_pivoted.py
dcs_catalog_client/models/catalog_v3_resource.py
dcs_catalog_client/models/catalog_v3_subject.py
dcs_catalog_client/models/catalog_v4.py
dcs_catalog_client/models/catalog_v5.py
dcs_catalog_client/models/catalog_version_endpoints.py
dcs_catalog_client/models/catalog_version_endpoints_response.py
dcs_catalog_client/models/external_tracker.py
dcs_catalog_client/models/external_wiki.py
dcs_catalog_client/models/internal_tracker.py
dcs_catalog_client/models/o_auth2_application.py
dcs_catalog_client/models/organization.py
dcs_catalog_client/models/permission.py
dcs_catalog_client/models/release.py
dcs_catalog_client/models/repo_transfer.py
dcs_catalog_client/models/repository.py
dcs_catalog_client/models/team.py
dcs_catalog_client/models/user.py
test/__init__.py
test/test_access_token.py
test/test_attachment.py
test/test_catalog_search_results_pivoted_v3.py
test/test_catalog_search_results_v3.py
test/test_catalog_search_results_v4.py
test/test_catalog_search_results_v5.py
test/test_catalog_stage.py
test/test_catalog_stages.py
test/test_catalog_v3.py
test/test_catalog_v3_language.py
test/test_catalog_v3_pivoted.py
dcs_catalog_client-1.16.8.dist-info/METADATA
dcs_catalog_client-1.16.8.dist-info/WHEEL
dcs_catalog_client-1.16.8.dist-info/top_level.txt
dcs_catalog_client-1.16.8.dist-info/RECORD
