Metadata-Version: 2.1
Name: dcs-catalog-client
Version: 1.16.8
Summary: Catalog Next API.
Home-page: https://github.com/unfoldingWord-dev/python-dcs-catalog-client
Author-email: 
Keywords: Swagger,Catalog Next API.
Requires-Dist: certifi (>=2017.4.17)
Requires-Dist: python-dateutil (>=2.1)
Requires-Dist: six (>=1.10)
Requires-Dist: urllib3 (>=1.23)
